cydrogen/__init__.py
cydrogen/__init__.pyi
cydrogen/_basekey.cpython-313-x86_64-linux-gnu.so
cydrogen/_basekey.pxd
cydrogen/_basekey.pyi
cydrogen/_context.cpython-313-x86_64-linux-gnu.so
cydrogen/_context.pxd
cydrogen/_context.pyi
cydrogen/_cyutility.cpython-313-x86_64-linux-gnu.so
cydrogen/_decls.cpython-313-x86_64-linux-gnu.so
cydrogen/_decls.pxd
cydrogen/_decls.pyi
cydrogen/_exceptions.cpython-313-x86_64-linux-gnu.so
cydrogen/_exceptions.pxd
cydrogen/_exceptions.pyi
cydrogen/_hash.cpython-313-x86_64-linux-gnu.so
cydrogen/_hash.pxd
cydrogen/_hash.pyi
cydrogen/_kx_n.cpython-313-x86_64-linux-gnu.so
cydrogen/_kx_n.pxd
cydrogen/_kx_n.pyi
cydrogen/_masterkey.cpython-313-x86_64-linux-gnu.so
cydrogen/_masterkey.pxd
cydrogen/_masterkey.pyi
cydrogen/_secretbox.cpython-313-x86_64-linux-gnu.so
cydrogen/_secretbox.pxd
cydrogen/_secretbox.pyi
cydrogen/_sign.cpython-313-x86_64-linux-gnu.so
cydrogen/_sign.pxd
cydrogen/_sign.pyi
cydrogen/_utils.cpython-313-x86_64-linux-gnu.so
cydrogen/_utils.pxd
cydrogen/_utils.pyi
cydrogen/version.py
cydrogen-0.0.10.dist-info/LICENSE
cydrogen-0.0.10.dist-info/METADATA
cydrogen-0.0.10.dist-info/WHEEL
cydrogen-0.0.10.dist-info/RECORD
