Metadata-Version: 2.1
Name: cydrogen
Version: 0.0.10
Summary: Cython bindings for the libhydrogen library
License:                                  Apache License
Classifier: Development Status :: 3 - Alpha
Classifier: Intended Audience :: Developers
Classifier: Programming Language :: Python :: 3.12
Classifier: Programming Language :: Python :: 3.13
Classifier: Programming Language :: Cython
Classifier: Programming Language :: Python :: Implementation :: CPython
Classifier: License :: OSI Approved :: Apache Software License
Classifier: Topic :: Software Development :: Libraries
Classifier: Topic :: Security :: Cryptography
Project-URL: Homepage, https://cydrogen.readthedocs.io
Project-URL: Documentation, https://cydrogen.readthedocs.io
Project-URL: Repository, https://github.com/stephane-martin/cydrogen
Project-URL: Issues, https://github.com/stephane-martin/cydrogen/issues
Project-URL: Changelog, https://github.com/stephane-martin/cydrogen/blob/develop/CHANGELOG.md
Requires-Python: >=3.12
